advys_configuracoes/__init__.py
advys_configuracoes/__version__.py
advys_configuracoes/config_ini.py
advys_configuracoes/constantes.py
advys_configuracoes/decorators.py
advys_configuracoes/inicializador.py
advys_configuracoes/logs.py
advys_estrutura/__init__.py
advys_estrutura/atualiza_caminhos.py
advys_estrutura/atualiza_estrutura.py
advys_estrutura/atualiza_imagens.py
advys_estrutura/caminhos.py
advys_estrutura/config.py
advys_estrutura/estrutura_dir.json
advys_estrutura/imagem.py
advys_estrutura/utils.py
advys_servicos/__init__.py
advys_servicos/email_smtp.py
advys_servicos/planilha_excel.py
advys_utilitarios/__init__.py
advys_utilitarios/arquivos_json.py
advys_utilitarios/bot_utils.py
advys_utilitarios/funcoes_pyautogui.py
advys_validadores/__init__.py
advys_validadores/arquivo.py
advys_validadores/emal.py
advys_validadores/senha.py
advys_web/dominio_web.py
advys_web/driver_personalizado.py
pyadvys-0.4.0.dist-info/licenses/LICENSE
pyadvys-0.4.0.dist-info/METADATA
pyadvys-0.4.0.dist-info/WHEEL
pyadvys-0.4.0.dist-info/entry_points.txt
pyadvys-0.4.0.dist-info/top_level.txt
pyadvys-0.4.0.dist-info/RECORD
