Metadata-Version: 2.4
Name: PyAdvys
Version: 0.4.0
Summary: Facilita o desenvolvimento de aplicações
Author-email: Chen <chenpsilva@gmail.com>
License: MIT
Classifier: Programming Language :: Python :: 3
Classifier: License :: OSI Approved :: MIT License
Classifier: Operating System :: OS Independent
Requires-Python: >=3.10
License-File: LICENSE
Dynamic: license-file
